squirrels_python-1.0.0.dist-info/METADATA
squirrels_python-1.0.0.dist-info/WHEEL
squirrels/squirrels.pyi
squirrels/__init__.py
squirrels/squirrels.cpython-310-s390x-linux-gnu.so
squirrels_python-1.0.0.dist-info/RECORD
